LICENSE
README.rst
setup.py
bert4vec/__init__.py
bert4vec/bert4vec.py
bert4vec/util.py
bert4vec.egg-info/PKG-INFO
bert4vec.egg-info/SOURCES.txt
bert4vec.egg-info/dependency_links.txt
bert4vec.egg-info/requires.txt
bert4vec.egg-info/top_level.txt